.DS_Store
pydatabot/__init__.py
pydatabot/bot.py
pydatabot/devbot-eayuea-91f036b58a20.json
pydatabot/emb_similarity.npy
pydatabot/manipulation_rec_similarity_pypi.py
pydatabot/templates_pandas.py
pydatabot/templates_spark.py
pydatabot-0.1.1.dist-info/LICENSE
pydatabot-0.1.1.dist-info/METADATA
pydatabot-0.1.1.dist-info/WHEEL
pydatabot-0.1.1.dist-info/top_level.txt
pydatabot-0.1.1.dist-info/RECORD
