Metadata-Version: 2.1
Name: pydatabot
Version: 0.1.1
Summary: Bot for DS
Home-page: https://github.com/XIN-von-SUN
Author: Xin SUN
Author-email: ethan.sun921107@gmail.com
License: UNKNOWN
Platform: UNKNOWN
Classifier: Programming Language :: Python :: 3
Classifier: License :: OSI Approved :: MIT License
Classifier: Operating System :: OS Independent
Requires-Dist: dialogflow
Requires-Dist: pandas
Requires-Dist: numpy
